{"copyright": {"licenseType": "NO", "determinationType": "GOV_PUBLIC_USE_PERMITTED", "thirdPartyContentCondition": "NOT_SET"}, "subjectCategories": ["SPACE SCIENCES"], "keywords": ["MISSION PLANNING", "SPACE EXPLORATION", "PROGRAM MANAGEMENT"], "exportControl": {"isExportControl": "NO", "ear": "NO", "itar": "NO"}, "distributionDate": "2011-09-08T00:00:00.0000000+00:00", "title": "Space - Questions and answers", "stiType": "OTHER", "distribution": "PUBLIC", "submittedDate": "2013-08-03T05:12:00.0000000+00:00", "authorAffiliations": [{"sequence": 0, "submissionId": 19660022213, "meta": {"author": {"name": "Cortright, E. M."}, "organization": {}}, "id": "6fe7894c3fd445fc9f72abf52091a843"}], "stiTypeDetails": "Other", "technicalReviewType": "TECHNICAL_REVIEW_TYPE_NONE", "modified": "2011-09-08T00:00:00.0000000+00:00", "id": 19660022213, "created": "2013-08-03T05:12:00.0000000+00:00", "center": {"code": "CDMS", "name": "Legacy CDMS", "id": "092d6e0881874968859b972d39a888dc"}, "onlyAbstract": false, "sensitiveInformation": 2, "abstract": "Question-answer series on general topics involving space exploration program", "isLessonsLearned": false, "disseminated": "METADATA_ONLY", "publications": [{"submissionId": 19660022213, "id": "1ac214dc771b4a1abf1c414dde87e430", "publicationDate": "1965-08-01T00:00:00.0000000+00:00"}], "status": "CURATED", "related": [{"disseminated": "DOCUMENT_AND_METADATA", "id": 19660022196, "type": "ANALYTIC_PRIMARY", "title": "Proceedings of the Conference on the Exploration of Mars and Venus", "stiType": "CONFERENCE_PROCEEDINGS", "distribution": "PUBLIC", "status": "CURATED"}, {"type": "ANALYTIC_PRIMARY", "accessionNumber": "N66-31486 18-30"}], "downloads": [], "downloadsAvailable": true, "index": "submissions-2022-09-30-06-07"}