{"copyright": {"disclosedInvention": false, "licenseType": "NO", "containsThirdPartyMaterial": false, "containsIndication": false, "determinationType": "PUBLIC_USE_PERMITTED", "thirdPartyContentCondition": "NOT_SET"}, "subjectCategories": ["SPACE SCIENCES"], "keywords": ["MISSION PLANNING", "MERCURY PROJECT", "APOLLO PROJECT", "GEMINI PROJECT"], "exportControl": {"isExportControl": "NO", "ear": "NO", "itar": "NO"}, "distributionDate": "2021-05-12T05:00:00.0000000+00:00", "fundingNumbers": [{"number": "Legacy Document", "type": "OTHER"}], "title": "Mission Planning", "stiType": "OTHER", "distribution": "PUBLIC", "submittedDate": "2021-04-23T15:59:54.6628560+00:00", "authorAffiliations": [{"organizationId": "73cf1aea628d4c0cad2d7573013af377", "sequence": 0, "submissionId": 19660020353, "meta": {"author": {"name": "Wyendell B. Evans"}, "organization": {"name": "Manned Spacecraft Center", "location": "Houston, Texas, United States"}}, "id": "44efb2fb5b444286afabb994d531f7b5", "userType": "OTHER"}, {"organizationId": "73cf1aea628d4c0cad2d7573013af377", "sequence": 1, "submissionId": 19660020353, "meta": {"author": {"name": "Howard W. Tindall"}, "organization": {"name": "Manned Spacecraft Center", "location": "Houston, Texas, United States"}}, "id": "577972be10db48c8a0248337120a027e", "userType": "OTHER"}, {"organizationId": "73cf1aea628d4c0cad2d7573013af377", "sequence": 2, "submissionId": 19660020353, "meta": {"author": {"name": "Helmut A. Kuehnel"}, "organization": {"name": "Manned Spacecraft Center", "location": "Houston, Texas, United States"}}, "id": "ba20dde8d27c400e8cceeb123542e1f4", "userType": "OTHER"}, {"organizationId": "73cf1aea628d4c0cad2d7573013af377", "sequence": 3, "submissionId": 19660020353, "meta": {"author": {"name": "Alfred A. Bishop"}, "organization": {"name": "Manned Spacecraft Center", "location": "Houston, Texas, United States"}}, "id": "6709b442a83348efbf090b4be84488ce", "userType": "OTHER"}], "stiTypeDetails": "Other - Legacy Document", "technicalReviewType": "TECHNICAL_REVIEW_TYPE_NONE", "modified": "2021-06-17T15:30:24.0739620+00:00", "id": 19660020353, "sourceIdentifiers": [], "created": "2013-08-03T05:18:00.0000000+00:00", "center": {"code": "JSC", "name": "Johnson Space Center", "id": "dd46994b91a94cb2a2722617cbbadc55"}, "onlyAbstract": false, "sensitiveInformation": 2, "abstract": "Mercury, Gemini, and Apollo mission planning development", "isLessonsLearned": false, "disseminated": "DOCUMENT_AND_METADATA", "publications": [{"submissionId": 19660020353, "id": "7445397a31154abc94fab2de2373ca7e", "publicationDate": "1966-01-01T00:00:00.0000000+00:00"}], "status": "CURATED", "related": [], "downloads": [{"draft": false, "mimetype": "application/pdf", "name": "19660020353.pdf", "notes": "previewed and not able to see any limiting markings. ", "type": "STI", "links": {"original": "/api/citations/19660020353/downloads/19660020353.pdf", "pdf": "/api/citations/19660020353/downloads/19660020353.pdf", "fulltext": "/api/citations/19660020353/downloads/19660020353.txt"}}], "downloadsAvailable": true, "index": "submissions-2022-09-30-06-07"}