{"copyright": {"licenseType": "NO", "determinationType": "OTHER", "thirdPartyContentCondition": "NOT_SET"}, "subjectCategories": ["SPACE SCIENCES"], "exportControl": {"isExportControl": "NO", "ear": "NO", "itar": "NO"}, "distributionDate": "2019-06-18T00:00:00.0000000+00:00", "fundingNumbers": [{"number": "NSF GP-32142", "type": "CONTRACT_GRANT"}, {"number": "NGL-24-005-008", "type": "CONTRACT_GRANT"}], "title": "Infrared observations of southern RV Tauri stars.", "stiType": "REPRINT", "distribution": "PUBLIC", "submittedDate": "2013-08-07T03:37:00.0000000+00:00", "authorAffiliations": [{"sequence": 0, "submissionId": 19730039042, "meta": {"author": {"name": "Gehrz, R. D."}, "organization": {}}, "id": "d4ea53bf9292483f873c55269eaa96a2"}, {"sequence": 1, "submissionId": 19730039042, "meta": {"author": {"name": "Ney, E. P."}, "organization": {}}, "id": "9bc4647df3984edf9ea2e4e4954166e6"}], "stiTypeDetails": "Reprint (Version printed in journal)", "technicalReviewType": "TECHNICAL_REVIEW_TYPE_NONE", "modified": "2011-08-12T00:00:00.0000000+00:00", "id": 19730039042, "sourceIdentifiers": [{"number": "doi:10.1086/129378", "type": "DOI"}], "created": "2013-08-07T03:37:00.0000000+00:00", "center": {"code": "CDMS", "name": "Legacy CDMS", "id": "092d6e0881874968859b972d39a888dc"}, "onlyAbstract": false, "sensitiveInformation": 2, "abstract": "Photometric measurements from 2.2 to 18 microns are reported for  six southern RV Tauri stars. Four of the six have anomalous infrared  excess radiation similar to that observed in other RV Tauri stars. The infrared spectra of IW Car, AR Pup, and SX Cen resemble that of oxygen-rich RV Tau. RU Cen is similar to AC Her.", "isLessonsLearned": false, "disseminated": "METADATA_ONLY", "publications": [{"submissionId": 19730039042, "id": "1aeb914900cb4ed68ee11bf19d768765", "publicationName": "Astronomical Society of the Pacific", "publicationDate": "1972-12-01T00:00:00.0000000+00:00"}], "status": "CURATED", "related": [], "downloads": [], "downloadsAvailable": false, "index": "submissions-2022-09-30-06-07"}