{"copyright": {"licenseType": "NO", "determinationType": "GOV_PUBLIC_USE_PERMITTED", "thirdPartyContentCondition": "NOT_SET"}, "subjectCategories": ["MACHINERY"], "exportControl": {"isExportControl": "NO", "ear": "NO", "itar": "NO"}, "created": "2013-08-09T13:32:00.0000000+00:00", "distributionDate": "2019-06-19T00:00:00.0000000+00:00", "otherReportNumbers": ["MSC-18087"], "center": {"code": "CDMS", "name": "Legacy CDMS", "id": "092d6e0881874968859b972d39a888dc"}, "onlyAbstract": false, "sensitiveInformation": 2, "abstract": "Valve was originally designed to handle liquid nitrogen tetroxide and mononethyl hydrazine. It successfully survived leakage at temperature as low as minus 95.5 C. It seals tightly against cold fluids, even after thousands of opening-and-closing cycles.", "title": "Low-leakage low-temperature valve", "stiType": "OTHER", "distribution": "PUBLIC", "submittedDate": "2013-08-09T13:32:00.0000000+00:00", "isLessonsLearned": false, "authorAffiliations": [{"sequence": 0, "submissionId": 19780000420, "meta": {"author": {"name": "Wang, W. S."}, "organization": {"name": "Consolidated Controls Corp."}}, "id": "23f456121ca446abb54d1fe65a078f10"}], "disseminated": "METADATA_ONLY", "stiTypeDetails": "Other - NASA Tech Brief", "technicalReviewType": "TECHNICAL_REVIEW_TYPE_NONE", "modified": "2011-08-16T00:00:00.0000000+00:00", "id": 19780000420, "publications": [{"volume": "3", "submissionId": 19780000420, "issue": "3", "issn": "0145-319X", "id": "bbfe0ea430da48ca8b9c61667367e4fa", "publicationName": "NASA Tech Briefs", "publicationDate": "1979-01-01T00:00:00.0000000+00:00"}], "status": "CURATED", "related": [], "downloads": [], "downloadsAvailable": false, "index": "submissions-2022-09-30-06-07"}