{"copyright": {"licenseType": "NO", "determinationType": "GOV_PUBLIC_USE_PERMITTED", "thirdPartyContentCondition": "NOT_SET"}, "subjectCategories": ["METEOROLOGY AND CLIMATOLOGY"], "exportControl": {"isExportControl": "NO", "ear": "NO", "itar": "NO"}, "created": "2013-08-09T15:47:00.0000000+00:00", "distributionDate": "2016-06-06T00:00:00.0000000+00:00", "center": {"code": "CDMS", "name": "Legacy CDMS", "id": "092d6e0881874968859b972d39a888dc"}, "onlyAbstract": false, "sensitiveInformation": 2, "abstract": "Meetings were held concerning aircraft design with considerable interest shown in aircraft operations. Topics covered were: (1) structural design for turbulence; (2) flight control; (3) data needs; and (4) lightning. Other factors discussed were temperature, rain, hail, icing, pressure, density, corrosives, and abrasives.", "title": "Summary report of the Aircraft Design Committee", "stiType": "CONFERENCE_PAPER", "distribution": "PUBLIC", "submittedDate": "2013-08-09T15:47:00.0000000+00:00", "isLessonsLearned": false, "authorAffiliations": [{"sequence": 0, "submissionId": 19780011781, "meta": {"author": {"name": "Woodcock, R. J."}, "organization": {"name": "Air Force Flight Dynamics Lab.", "location": "Wright-Patterson AFB, OH, United States"}}, "id": "a3cc8c6ec53442d28dc8af9524ba87dc"}], "disseminated": "DOCUMENT_AND_METADATA", "stiTypeDetails": "Conference Paper", "technicalReviewType": "TECHNICAL_REVIEW_TYPE_NONE", "modified": "2011-09-08T00:00:00.0000000+00:00", "id": 19780011781, "publications": [{"submissionId": 19780011781, "id": "bf406bc6640e4f28b4a56050e118a99c", "publicationName": "Tennessee Univ. Space Inst.  Proc. of the 1st Ann. Meteorol. and Environ. Inputs to Aviation Systems Workshop", "publicationDate": "1977-03-01T00:00:00.0000000+00:00"}], "status": "CURATED", "related": [{"disseminated": "DOCUMENT_AND_METADATA", "id": 19780011768, "type": "ANALYTIC_PRIMARY", "title": "Proceedings of the First Annual Meteorological and Environmental Inputs to Aviation Systems Workshop", "stiType": "CONFERENCE_PROCEEDINGS", "distribution": "PUBLIC", "status": "CURATED"}], "downloads": [{"draft": false, "mimetype": "application/pdf", "name": "19780011781.pdf", "type": "STI", "links": {"original": "/api/citations/19780011781/downloads/19780011781.pdf", "pdf": "/api/citations/19780011781/downloads/19780011781.pdf", "fulltext": "/api/citations/19780011781/downloads/19780011781.txt"}}], "downloadsAvailable": true, "index": "submissions-2022-09-30-06-07"}