{"copyright": {"licenseType": "NO", "determinationType": "OTHER", "thirdPartyContentCondition": "NOT_SET"}, "subjectCategories": ["EARTH RESOURCES AND REMOTE SENSING"], "exportControl": {"isExportControl": "NO", "ear": "NO", "itar": "NO"}, "created": "2013-08-09T20:21:00.0000000+00:00", "distributionDate": "2019-07-12T00:00:00.0000000+00:00", "center": {"code": "CDMS", "name": "Legacy CDMS", "id": "092d6e0881874968859b972d39a888dc"}, "onlyAbstract": false, "sensitiveInformation": 2, "abstract": "The papers outline the remote sensing activities being carried out in a number of countries throughout the world, and present details on a variety of individual projects. Topics studied include a worldwide approach to remote sensing and mineral exploration, a land use information system based on statistical inference, acoustic radar and remote sensing in the boundary layer, procedure for land-use analysis in developing countries, an airborne geochemical system, remote sensing of snowpack with microwave radiometers for hydrologic applications, wheat production forecasts based on Landsat data, airborne lidar aerosol measurements over the U.S. and Europe, Landsat inventory of agricultural and forest resources in Bangladesh, application of satellite imagery to flood plain mapping in Thailand, and vegetation mapping of Nigeria from radar.", "title": "International Symposium on Remote Sensing of Environment, 12th, Manila, Philippines, April 20-26, 1978, Proceedings. Volumes 1, 2 & 3", "stiType": "CONFERENCE_PROCEEDINGS", "distribution": "PUBLIC", "submittedDate": "2013-08-09T20:21:00.0000000+00:00", "isLessonsLearned": false, "disseminated": "METADATA_ONLY", "stiTypeDetails": "Conference Proceedings", "technicalReviewType": "TECHNICAL_REVIEW_TYPE_NONE", "modified": "2011-08-16T00:00:00.0000000+00:00", "meetings": [{"country": "Philippines", "submissionId": 19790038472, "endDate": "1978-04-26T00:00:00.0000000+00:00", "sponsors": [{"meta": {"organization": {"name": "Environmental Research Institute of Michigan"}}, "meetingId": "ca3ad18e656a4952a3d40056397933a3", "id": "f74d1bf402b64460a177b0aab2af583e"}, {"meta": {"organization": {"name": "NASA"}}, "meetingId": "ca3ad18e656a4952a3d40056397933a3", "id": "ceb157aefdb0478daff5326fd0827289"}, {"meta": {"organization": {"name": "Department of Natural Resources of the Phillipines"}}, "meetingId": "ca3ad18e656a4952a3d40056397933a3", "id": "a604fe1f57374865b7ff2f96b28d194d"}], "name": "International Symposium on Remote Sensing of Environment", "location": "Manila", "id": "ca3ad18e656a4952a3d40056397933a3", "startDate": "1978-04-20T00:00:00.0000000+00:00"}], "id": 19790038472, "publications": [{"submissionId": 19790038472, "id": "11c75ff4a99c4c209b7c727336428c36", "publicationDate": "1978-01-01T00:00:00.0000000+00:00"}], "status": "CURATED", "related": [], "downloads": [], "downloadsAvailable": false, "index": "submissions-2022-09-30-06-07"}