{"copyright": {"licenseType": "NO", "determinationType": "GOV_PUBLIC_USE_PERMITTED", "thirdPartyContentCondition": "NOT_SET"}, "subjectCategories": ["OCEANOGRAPHY"], "exportControl": {"isExportControl": "NO", "ear": "NO", "itar": "NO"}, "distributionDate": "2019-06-21T00:00:00.0000000+00:00", "otherReportNumbers": ["NASA-TM-73295"], "title": "Gulf of Mexico satellite radar altimetry", "stiType": "TECHNICAL_MEMORANDUM", "distribution": "PUBLIC", "submittedDate": "2013-09-04T14:59:00.0000000+00:00", "authorAffiliations": [{"sequence": 0, "submissionId": 19810025217, "meta": {"author": {"name": "Parra, C. G."}, "organization": {"name": "NASA Wallops Flight Center", "location": "Wallops Island, VA, United States"}}, "id": "82460a6fb1404cd1b476a9d66631e21e"}, {"sequence": 1, "submissionId": 19810025217, "meta": {"author": {"name": "Forsythe, R. G."}, "organization": {"name": "NASA Wallops Flight Center", "location": "Wallops Island, VA, United States"}}, "id": "664db2c6203c4774a793b492b2520347"}, {"sequence": 2, "submissionId": 19810025217, "meta": {"author": {"name": "Parsons, C. L."}, "organization": {"name": "NASA Wallops Flight Center", "location": "Wallops Island, VA, United States"}}, "id": "6587668608304e54992bf43f5e04ffcd"}], "stiTypeDetails": "Technical Memorandum (TM)", "technicalReviewType": "TECHNICAL_REVIEW_TYPE_NONE", "modified": "2013-08-29T00:00:00.0000000+00:00", "id": 19810025217, "created": "2013-09-04T14:59:00.0000000+00:00", "center": {"code": "CDMS", "name": "Legacy CDMS", "id": "092d6e0881874968859b972d39a888dc"}, "onlyAbstract": false, "sensitiveInformation": 2, "abstract": "The dynamic topography of the sea surface was measured. The radar altimeter measurements yield average ocean topographic data which are mapped. Seasonal deviations from a 3 year mean topography are presented. The altimeters are also instrumented with sample and hold gates which provide information about the shape and amplitude of the return waveform. Parameters including ocean surface wind speed and the significant wave height are determined. One hundred eighty six wind speed and significant wave height histograms are presented.", "isLessonsLearned": false, "disseminated": "DOCUMENT_AND_METADATA", "publications": [{"submissionId": 19810025217, "id": "07f9685ec31f4e43821f437c41db0a21", "publicationDate": "1981-08-01T00:00:00.0000000+00:00"}], "status": "CURATED", "related": [], "downloads": [{"draft": false, "mimetype": "application/pdf", "name": "19810025217.pdf", "type": "STI", "links": {"original": "/api/citations/19810025217/downloads/19810025217.pdf", "pdf": "/api/citations/19810025217/downloads/19810025217.pdf", "fulltext": "/api/citations/19810025217/downloads/19810025217.txt"}}], "downloadsAvailable": true, "index": "submissions-2022-09-30-06-07"}