{"copyright": {"licenseType": "NO", "determinationType": "GOV_PUBLIC_USE_PERMITTED", "thirdPartyContentCondition": "NOT_SET"}, "subjectCategories": ["MATHEMATICS AND INFORMATION SCIENCES"], "exportControl": {"isExportControl": "NO", "ear": "NO", "itar": "NO"}, "created": "2013-08-15T17:41:00.0000000+00:00", "distributionDate": "2019-07-11T00:00:00.0000000+00:00", "otherReportNumbers": ["ARC-12571"], "center": {"code": "CDMS", "name": "Legacy CDMS", "id": "092d6e0881874968859b972d39a888dc"}, "onlyAbstract": false, "sensitiveInformation": 2, "abstract": "Visual Object Oriented Unification System (VOUS) computer program provides facility for development of other, high-level software. Does not replace, but rather extends, preexisting software tools for development of other software. Provides comprehensive, graphical, interactive medium for all phases in development of computer code from early exploration of concepts, through detailed coding-and-error-checking process, to final reporting of finished code and compilation of instruction manual for its use. Simplifies and partly automates programmer's task.", "title": "VOUS Software Facilitates Development Of Other Software", "stiType": "OTHER", "distribution": "PUBLIC", "submittedDate": "2013-08-15T17:41:00.0000000+00:00", "isLessonsLearned": false, "authorAffiliations": [{"sequence": 0, "submissionId": 19920000055, "meta": {"author": {"name": "Oliger, Joseph"}, "organization": {"name": "Stanford Univ."}}, "id": "293ea49be0474942a443f55f88d8ff73"}, {"sequence": 1, "submissionId": 19920000055, "meta": {"author": {"name": "Pichumani, Ramini"}, "organization": {"name": "Stanford Univ."}}, "id": "1c1c69783eb944e3b7509331f6679df1"}, {"sequence": 2, "submissionId": 19920000055, "meta": {"author": {"name": "Ponceleon, Dulce"}, "organization": {"name": "Stanford Univ."}}, "id": "4a1e0b2224564d65af754d586d6406c3"}], "disseminated": "METADATA_ONLY", "stiTypeDetails": "Other - NASA Tech Brief", "technicalReviewType": "TECHNICAL_REVIEW_TYPE_NONE", "modified": "2011-08-19T00:00:00.0000000+00:00", "id": 19920000055, "publications": [{"volume": "16", "submissionId": 19920000055, "issue": "1", "issn": "0145-319X", "id": "25f9e181db7c47b48512952188a91d8b", "publicationName": "NASA Tech Briefs", "publicationDate": "1992-01-01T00:00:00.0000000+00:00"}], "status": "CURATED", "related": [], "downloads": [], "downloadsAvailable": false, "index": "submissions-2022-09-30-06-07"}