{"copyright": {"licenseType": "NO", "determinationType": "GOV_PUBLIC_USE_PERMITTED", "thirdPartyContentCondition": "NOT_SET"}, "keywords": ["SEAPLANES - LIORE & OLIVIER LeO 194 (FR )", "SEAPLANES - DESCR"], "exportControl": {"isExportControl": "NO", "ear": "NO", "itar": "NO"}, "created": "2013-09-06T18:24:00.0000000+00:00", "distributionDate": "2019-06-26T00:00:00.0000000+00:00", "otherReportNumbers": ["NACA-AC-39"], "center": {"code": "CDMS", "name": "Legacy CDMS", "id": "092d6e0881874968859b972d39a888dc"}, "onlyAbstract": false, "sensitiveInformation": 2, "abstract": "It's fuselage is made entirely of wood. It has 6 gasoline tanks each with a capacity of 255 liters. It is a single engine biplane with wings mounted above the body of the seaplane.", "title": "Liore-Olivier LeO 194 seaplane", "stiType": "OTHER", "distribution": "PUBLIC", "submittedDate": "2013-09-06T18:24:00.0000000+00:00", "isLessonsLearned": false, "disseminated": "DOCUMENT_AND_METADATA", "stiTypeDetails": "Other", "technicalReviewType": "TECHNICAL_REVIEW_TYPE_NONE", "modified": "2013-08-29T00:00:00.0000000+00:00", "id": 19930090615, "publications": [{"submissionId": 19930090615, "id": "dc09cad6373f4d789b4bcc740ec5b42e", "publicationDate": "1927-04-01T00:00:00.0000000+00:00"}], "status": "CURATED", "related": [], "downloads": [{"draft": false, "mimetype": "application/pdf", "name": "19930090615.pdf", "type": "STI", "links": {"original": "/api/citations/19930090615/downloads/19930090615.pdf", "pdf": "/api/citations/19930090615/downloads/19930090615.pdf", "fulltext": "/api/citations/19930090615/downloads/19930090615.txt"}}], "downloadsAvailable": true, "index": "submissions-2022-09-30-06-07"}