{"copyright": {"licenseType": "NO", "determinationType": "OTHER", "thirdPartyContentCondition": "NOT_SET"}, "subjectCategories": ["Lunar and Planetary Science and Exploration"], "keywords": ["Mars Global Surveyor"], "exportControl": {"isExportControl": "NO", "ear": "NO", "itar": "NO"}, "distributionDate": "2018-06-07T00:00:00.0000000+00:00", "title": "Mars Global Surveyor: Cruising to Mars", "stiType": "PREPRINT", "distribution": "PUBLIC", "submittedDate": "2013-08-23T18:06:00.0000000+00:00", "authorAffiliations": [{"sequence": 0, "submissionId": 20060034997, "meta": {"author": {"name": "Cunningham, Glenn E."}, "organization": {}}, "id": "b6cc2e2937a94efe9fbfdc906ef42000"}], "stiTypeDetails": "Preprint (Draft being sent to journal)", "technicalReviewType": "TECHNICAL_REVIEW_TYPE_NONE", "modified": "2011-08-23T00:00:00.0000000+00:00", "id": 20060034997, "sourceIdentifiers": [{"number": "hdl:2014/21808", "type": "HANDLE"}], "created": "2013-08-23T18:06:00.0000000+00:00", "center": {"code": "JPL", "name": "Jet Propulsion Laboratory", "id": "efbc9c123a0f47caafa95d99b7d2e1a1"}, "onlyAbstract": false, "sensitiveInformation": 2, "abstract": "The Mars Global Surveyor spacecraft was launched on November 7, 1996, and is now cruising to Mars.  While the launch was excellent, and the spacecraft and its science payload are in  perfect operating condition, a broken deployment damper on one of the two solar arrays has posed some concern relative to the use of that solar array as a drag surfae during aerobraking  operations at Mars.", "isLessonsLearned": false, "disseminated": "METADATA_ONLY", "publications": [{"submissionId": 20060034997, "id": "8d757e262df54552b0c2c62cbb65d760", "publicationDate": "1997-05-29T00:00:00.0000000+00:00"}], "status": "CURATED", "related": [], "downloads": [], "downloadsAvailable": false, "index": "submissions-2022-09-30-06-07"}