{"copyright": {"licenseType": "NO", "determinationType": "OTHER", "thirdPartyContentCondition": "NOT_SET"}, "subjectCategories": ["Cybernetics, Artificial Intelligence and Robotics"], "keywords": ["robotics robotic arm sampling MVACS"], "exportControl": {"isExportControl": "NO", "ear": "NO", "itar": "NO"}, "distributionDate": "2018-06-07T00:00:00.0000000+00:00", "title": "MVACS Robotic Arm", "stiType": "REPRINT", "distribution": "PUBLIC", "submittedDate": "2013-08-23T18:42:00.0000000+00:00", "authorAffiliations": [{"sequence": 0, "submissionId": 20060040426, "meta": {"author": {"name": "Bonitz, R."}, "organization": {}}, "id": "4c8f5352258042eda49d0e1f1c80e3c7"}, {"sequence": 1, "submissionId": 20060040426, "meta": {"author": {"name": "Slostad, J."}, "organization": {}}, "id": "01ddfb188ea243599dbc37fbfbc62a36"}, {"sequence": 2, "submissionId": 20060040426, "meta": {"author": {"name": "Bon, B."}, "organization": {}}, "id": "c088ed3ba9b84aa3981f86623dd46614"}, {"sequence": 3, "submissionId": 20060040426, "meta": {"author": {"name": "Braun, D."}, "organization": {}}, "id": "112c2a279bd5430bb7c1e0577e88ba34"}, {"sequence": 4, "submissionId": 20060040426, "meta": {"author": {"name": "Brill, R."}, "organization": {}}, "id": "bae7890751e74f37bda966c8df96518f"}, {"sequence": 5, "submissionId": 20060040426, "meta": {"author": {"name": "Buck, C."}, "organization": {}}, "id": "c5cc5b9a1c44475087141b8c3693e15d"}, {"sequence": 6, "submissionId": 20060040426, "meta": {"author": {"name": "Fleischner, R."}, "organization": {}}, "id": "59bbd9d1a6b441d39b0cccc3faedf016"}, {"sequence": 7, "submissionId": 20060040426, "meta": {"author": {"name": "Haldeman, A."}, "organization": {}}, "id": "6b0ec3ca11184de282571e597a90977a"}, {"sequence": 8, "submissionId": 20060040426, "meta": {"author": {"name": "Herman, J."}, "organization": {}}, "id": "8097267e380844dc891e0501d26a0d8d"}, {"sequence": 9, "submissionId": 20060040426, "meta": {"author": {"name": "Hertzel, M."}, "organization": {}}, "id": "4f605533e9034a5cbe7080facfe6cf19"}, {"sequence": 10, "submissionId": 20060040426, "meta": {"author": {"name": "Noon, D."}, "organization": {}}, "id": "1ea235c59ad4460bb1369761a6da4ce5"}, {"sequence": 11, "submissionId": 20060040426, "meta": {"author": {"name": "Pixler, G."}, "organization": {}}, "id": "af1f5e8a072a4adaa96bc892dd37bc2b"}, {"sequence": 12, "submissionId": 20060040426, "meta": {"author": {"name": "Schenker, P."}, "organization": {}}, "id": "1a61a8c3b0c548ebb703d39a99f49080"}, {"sequence": 13, "submissionId": 20060040426, "meta": {"author": {"name": "Ton, T."}, "organization": {}}, "id": "6706cbbdc16e49fa844c7473f44c544f"}, {"sequence": 14, "submissionId": 20060040426, "meta": {"author": {"name": "Tucker, C."}, "organization": {}}, "id": "a0c7a3c5998c4bc4a34ac7c424b36021"}, {"sequence": 15, "submissionId": 20060040426, "meta": {"author": {"name": "Zimmerman, W."}, "organization": {}}, "id": "f34ea4fee5d642d5884c290a3771c03a"}], "stiTypeDetails": "Reprint (Version printed in journal)", "technicalReviewType": "TECHNICAL_REVIEW_TYPE_NONE", "modified": "2011-08-23T00:00:00.0000000+00:00", "id": 20060040426, "sourceIdentifiers": [{"number": "hdl:2014/13866", "type": "HANDLE"}], "created": "2013-08-23T18:42:00.0000000+00:00", "center": {"code": "JPL", "name": "Jet Propulsion Laboratory", "id": "efbc9c123a0f47caafa95d99b7d2e1a1"}, "onlyAbstract": false, "sensitiveInformation": 2, "abstract": "The primary purpose of the Mars Volatiles and Climate Surveyor (MVACS) Robotic Arm is to support to the other MVACS science instruments by digging trenches in the Martian soil;  acquiring and dumping soil samples into the thermal evolved gas analyzer (TEGA); positioning the Soil Temperature Probe (STP) in the soil: positioning the Robotic Arm Air Temperature  Sensor (RAATS) at various heights above the surface, and positioning the Robotic Arm Camera (RAC) for taking images of the surface, trench, soil samples, magnetic targets and other  objects of scientific interest within its workspace.", "isLessonsLearned": false, "disseminated": "METADATA_ONLY", "publications": [{"submissionId": 20060040426, "id": "c3fdd5cf09fc4acabd07711f3075d2b4", "publicationName": "Journal of Geophysical Research-Planets", "publicationDate": "2000-01-01T00:00:00.0000000+00:00"}], "status": "CURATED", "related": [], "downloads": [], "downloadsAvailable": false, "index": "submissions-2022-09-30-06-07"}