{"copyright": {"licenseType": "NO", "patent": "US-Patent-7,397,774", "patentApplication": "US-Patent-Appl-SN-10/446,283", "determinationType": "GOV_PUBLIC_USE_PERMITTED", "thirdPartyContentCondition": "NOT_SET"}, "subjectCategories": ["Mathematical and Computer Sciences (General)"], "exportControl": {"isExportControl": "NO", "ear": "NO", "itar": "NO"}, "created": "2013-08-24T20:04:00.0000000+00:00", "distributionDate": "2019-08-26T18:51:42.9100000+00:00", "center": {"code": "HQ", "name": "Headquarters", "id": "f0865a34ba1f474d865ab51f212fc69f"}, "onlyAbstract": false, "sensitiveInformation": 2, "abstract": "A data multiplexer that accommodates both industry standard CCSDS data packets and bits streams and standard IEEE 1394 data is described. The multiplexer provides a statistical allotment of bandwidth to the channels in turn, preferably four, but expandable in increments of four up to sixteen. A microcontroller determines bandwidth requested by the plurality of channels, as well as the bandwidth available, and meters out the available bandwidth on a statistical basis employing flow control to the input channels.", "title": "Downlink data multiplexer", "stiType": "OTHER", "distribution": "PUBLIC", "submittedDate": "2013-08-24T20:04:00.0000000+00:00", "isLessonsLearned": false, "authorAffiliations": [{"sequence": 0, "submissionId": 20090002644, "meta": {"author": {"name": "Holland, S. Douglas"}, "organization": {}}, "id": "730d07ce4a194c3da61e15a27ee6f11e"}, {"sequence": 1, "submissionId": 20090002644, "meta": {"author": {"name": "Steele, Glen F."}, "organization": {}}, "id": "b3651a8223374186b4c2496d25923e8b"}, {"sequence": 2, "submissionId": 20090002644, "meta": {"author": {"name": "Romero, Denise M."}, "organization": {}}, "id": "58c3cbf08c784f03b920a7a56c4a0be3"}, {"sequence": 3, "submissionId": 20090002644, "meta": {"author": {"name": "Koudelka, Robert David"}, "organization": {}}, "id": "d1c7b701326a4b18aab9a3d59311254d"}], "disseminated": "DOCUMENT_AND_METADATA", "stiTypeDetails": "Other - Patent", "technicalReviewType": "TECHNICAL_REVIEW_TYPE_NONE", "modified": "2011-09-08T00:00:00.0000000+00:00", "id": 20090002644, "publications": [{"submissionId": 20090002644, "id": "8962b4a662184c78b36aff25a7550907", "publicationDate": "2008-07-08T00:00:00.0000000+00:00"}], "status": "CURATED", "related": [], "downloads": [{"draft": false, "mimetype": "application/pdf", "name": "20090002644.pdf", "type": "STI", "links": {"original": "/api/citations/20090002644/downloads/20090002644.pdf", "pdf": "/api/citations/20090002644/downloads/20090002644.pdf", "fulltext": "/api/citations/20090002644/downloads/20090002644.txt"}}], "downloadsAvailable": true, "index": "submissions-2022-09-30-06-07"}