{"copyright": {"licenseType": "NO", "determinationType": "GOV_PUBLIC_USE_PERMITTED", "thirdPartyContentCondition": "NOT_SET"}, "subjectCategories": ["Lunar and Planetary Science and Exploration"], "exportControl": {"isExportControl": "NO", "ear": "NO", "itar": "NO"}, "distributionDate": "2020-02-18T13:01:13.2200000+00:00", "otherReportNumbers": ["KSC-E-DAA-TN77971"], "title": "NASA Dust Mitigation Strategy", "stiType": "PRESENTATION", "distribution": "PUBLIC", "submittedDate": "2020-02-14T13:56:11.0230000+00:00", "authorAffiliations": [{"sequence": 0, "submissionId": 20200000892, "meta": {"author": {"name": "Johansen, Michael R."}, "organization": {"name": "NASA Kennedy Space Center", "location": "Cocoa Beach, FL, United States"}}, "id": "e8d8a5da57c04952a3ec6b1d0a7ee06b"}], "stiTypeDetails": "Presentation", "technicalReviewType": "SINGLE_EXPERT", "id": 20200000892, "created": "2020-02-14T13:56:11.0230000+00:00", "center": {"code": "KSC", "name": "Kennedy Space Center", "id": "a74d241e0e974719b03cb45cbace6b20"}, "onlyAbstract": false, "sensitiveInformation": 2, "abstract": "No abstract available", "isLessonsLearned": false, "disseminated": "DOCUMENT_AND_METADATA", "meetings": [{"country": "United States", "submissionId": 20200000892, "endDate": "2020-02-13T00:00:00.0000000+00:00", "sponsors": [{"meta": {"organization": {"name": "Lunar and Planetary Institute (LPI)", "location": "Houston, TX, United States"}}, "meetingId": "12e73c1e4a5d4d999a0566f1df69bac2", "id": "34a48076ebde40f59911baf33b50b7e0"}], "name": "Impacts of Lunar Dust on Human Exploration", "location": "Houston, TX", "id": "12e73c1e4a5d4d999a0566f1df69bac2", "startDate": "2020-02-11T00:00:00.0000000+00:00"}], "publications": [{"submissionId": 20200000892, "id": "ec4f278aab554cf9b8860cc3dd1971a9", "publicationDate": "2020-02-11T00:00:00.0000000+00:00"}], "status": "CURATED", "related": [], "downloads": [{"draft": false, "mimetype": "application/pdf", "name": "20200000892.pdf", "type": "STI", "links": {"original": "/api/citations/20200000892/downloads/20200000892.pdf", "pdf": "/api/citations/20200000892/downloads/20200000892.pdf", "fulltext": "/api/citations/20200000892/downloads/20200000892.txt"}}], "downloadsAvailable": true, "index": "submissions-2022-09-30-06-07"}