{"copyright": {"licenseType": "NO", "approverComments": "Items in TRS are protected by copyright, but are furnished with U.S. government purpose use rights.", "containsIndication": true, "belongsToPublisher": true, "determinationType": "OTHER", "thirdPartyContentCondition": "NOT_SET"}, "keywords": [], "exportControl": {"isExportControl": "UNSET", "ear": "UNSET", "itar": "UNSET"}, "created": "2019-07-08T00:00:00.0000000+00:00", "distributionDate": "2019-07-08T00:00:00.0000000+00:00", "center": {"code": "JPL", "name": "Jet Propulsion Laboratory", "id": "efbc9c123a0f47caafa95d99b7d2e1a1"}, "onlyAbstract": false, "sensitiveInformation": 0, "title": "Insight Approach Operations During Dust-Storm Season", "stiType": "PRESENTATION", "distribution": "PUBLIC", "authorAffiliations": [{"sequence": 0, "submissionId": 20210012067, "meta": {"author": {"name": "Sklyanskiy, Evgeniy"}}, "id": "7beb3bf5ea8e4b1bab04e12180f4ae99"}, {"sequence": 0, "submissionId": 20210012067, "meta": {"author": {"name": "Kipp, Devin"}}, "id": "8dc2886c6f25475ab91639c1c9d0cdfe"}, {"sequence": 0, "submissionId": 20210012067, "meta": {"author": {"name": "Bonfiglio, Eugene P."}}, "id": "6d01fe38b70c4cabb6a243d687233d1a"}], "disseminated": "METADATA_ONLY", "stiTypeDetails": "Presentation", "technicalReviewType": "NOT_SET", "modified": "2022-09-30T05:33:07.9821000+00:00", "id": 20210012067, "sourceIdentifiers": [{"number": "2014/51033", "type": "HANDLE"}], "publications": [{"submissionId": 20210012067, "publisher": "Pasadena, CA: Jet Propulsion Laboratory, National Aeronautics and Space Administration, 2019", "id": "c445cfe9918441a7973c347042b0324e", "publicationDate": "2019-07-08T00:00:00.0000000+00:00"}], "status": "CURATED", "related": [], "downloads": [], "downloadsAvailable": false, "index": "submissions-2022-09-30-06-07"}