{"keywords": ["space and planetary science", "astronomy and astrophysics"], "created": "2022-09-30T04:22:36.779630+00:00", "distributionDate": "2019-05-06T00:00:00", "fundingNumbers": [{"number": "1545949", "type": "funding"}, {"number": "HST- HF2-51404.001-A", "type": "funding"}], "title": "A Strategy for LSST to Unveil a Population of Kilonovae without Gravitational-wave Triggers", "distribution": "PUBLIC", "stiType": "ACCEPTED_MANUSCRIPT", "disseminated": "DOCUMENT_AND_METADATA", "authorAffiliations": [{"sequence": 0, "meta": {"author": {"name": "Igor Andreoni"}, "organization": {"name": ""}}}, {"sequence": 1, "meta": {"author": {"name": "Shreya Anand"}, "organization": {"name": ""}}}, {"sequence": 2, "meta": {"author": {"name": "Federica B. Bianco"}, "organization": {"name": ""}}}, {"sequence": 3, "meta": {"author": {"name": "S. Bradley Cenko"}, "organization": {"name": ""}}}, {"sequence": 4, "meta": {"author": {"name": "Philip S. Cowperthwaite"}, "organization": {"name": ""}}}, {"sequence": 5, "meta": {"author": {"name": "Michael W. Coughlin"}, "organization": {"name": ""}}}, {"sequence": 6, "meta": {"author": {"name": "Maria Drout"}, "organization": {"name": ""}}}, {"sequence": 7, "meta": {"author": {"name": "V. Zach Golkhou"}, "organization": {"name": ""}}}, {"sequence": 8, "meta": {"author": {"name": "David L. Kaplan"}, "organization": {"name": ""}}}, {"sequence": 9, "meta": {"author": {"name": "Kunal P. Mooley"}, "organization": {"name": ""}}}, {"sequence": 10, "meta": {"author": {"name": "Tyler A. Pritchard"}, "organization": {"name": ""}}}, {"sequence": 11, "meta": {"author": {"name": "Leo P. Singer"}, "organization": {"name": ""}}}, {"sequence": 12, "meta": {"author": {"name": "Sara Webb"}, "organization": {"name": ""}}}, {"sequence": 13, "meta": {"author": {"name": "None None"}, "organization": {"name": ""}}}], "stiTypeDetails": "Accepted Manuscript", "modified": "2022-08-02T00:00:00", "id": "22930881473078", "sourceIdentifiers": [{"number": "http://dx.doi.org/10.1088/1538-3873/ab1531"}], "publications": [{"volume": "131", "pages": "068004", "issue": "1000", "issn": "0004-6280", "publisher": "IOP Publishing", "eissn": "1538-3873", "publicationName": "Publications of the Astronomical Society of the Pacific", "publicationDate": "2019-05-06T00:00:00", "issuePublicationDate": "2019-06-01T00:00:00", "doi": "10.1088/1538-3873/ab1531"}], "status": "CURATED", "related": [], "downloads": [], "downloadsAvailable": false, "index": "chorus-2022-09-30-04-32"}