{"keywords": ["computational theory and mathematics", "computer science applications", "information systems"], "created": "2022-09-30T04:21:37.736429+00:00", "distributionDate": "2019-08-01T00:00:00", "fundingNumbers": [{"number": "NNX16CD07C", "type": "funding"}, {"number": "IIS-1734558", "type": "funding"}, {"number": "2014-67021-22174", "type": "funding"}, {"number": "IIS-1553528", "type": "funding"}], "title": "Analysis of University Fitness Center Data Uncovers Interesting Patterns, Enables Prediction", "distribution": "PUBLIC", "stiType": "REPRINT", "disseminated": "DOCUMENT_AND_METADATA", "authorAffiliations": [{"sequence": 0, "meta": {"author": {"name": "Yunshu Du"}, "organization": {"name": ""}}}, {"sequence": 1, "meta": {"author": {"name": "Assefaw H. Gebremedhin"}, "organization": {"name": ""}}}, {"sequence": 2, "meta": {"author": {"name": "Matthew E. Taylor"}, "organization": {"name": ""}}}], "stiTypeDetails": "Version of Record", "modified": "2022-07-15T00:00:00", "id": "25592007525909", "sourceIdentifiers": [{"number": "http://dx.doi.org/10.1109/tkde.2018.2863705"}], "publications": [{"volume": "31", "pages": "1478-1490", "issue": "8", "issn": "1041-4347", "publisher": "Institute of Electrical and Electronics Engineers (IEEE)", "eissn": "1558-2191", "publicationName": "IEEE Transactions on Knowledge and Data Engineering", "issuePublicationDate": "2019-08-01T00:00:00", "doi": "10.1109/tkde.2018.2863705"}], "status": "CURATED", "related": [], "downloads": [], "downloadsAvailable": false, "index": "chorus-2022-09-30-04-32"}